compositefk/__init__.py
compositefk/fields.py
compositefk/related_descriptors.py
django_composite_foreignkey-1.0.0a10.dist-info/DESCRIPTION.rst
django_composite_foreignkey-1.0.0a10.dist-info/METADATA
django_composite_foreignkey-1.0.0a10.dist-info/RECORD
django_composite_foreignkey-1.0.0a10.dist-info/WHEEL
django_composite_foreignkey-1.0.0a10.dist-info/metadata.json
django_composite_foreignkey-1.0.0a10.dist-info/top_level.txt
