Metadata-Version: 2.0
Name: django-composite-foreignkey
Version: 1.0.0a10
Summary: composite foreignkey support for django
Home-page: https://github.com/onysos/django-composite-foreignkey
Author: Darius BERNARD
Author-email: contact@xornot.fr
License: GNU GENERAL PUBLIC LICENSE
Keywords: django composite foreignkey
Platform: UNKNOWN
Classifier: Development Status :: 4 - Beta
Classifier: Intended Audience :: Developers
Classifier: License :: OSI Approved :: GNU General Public License v3 (GPLv3)
Classifier: Programming Language :: Python :: 2
Classifier: Programming Language :: Python :: 2.7
Classifier: Programming Language :: Python :: 3
Classifier: Programming Language :: Python :: 3.2
Classifier: Programming Language :: Python :: 3.3
Classifier: Programming Language :: Python :: 3.4
Classifier: Programming Language :: Python :: 3.5
Classifier: Operating System :: OS Independent
Classifier: Topic :: Software Development :: Libraries
Classifier: Topic :: Utilities
Classifier: Environment :: Web Environment
Classifier: Framework :: Django
